poetry_opeco17_test_plugin/__init__.py
poetry_opeco17_test_plugin/plugin.py
poetry_opeco17_test_plugin-1.0.2.dist-info/entry_points.txt
poetry_opeco17_test_plugin-1.0.2.dist-info/WHEEL
poetry_opeco17_test_plugin-1.0.2.dist-info/METADATA
poetry_opeco17_test_plugin-1.0.2.dist-info/RECORD
