Metadata-Version: 2.1
Name: poetry-opeco17-test-plugin
Version: 1.0.2
Summary: 
Author: opeco17
Author-email: opeco17@gmail.com
Requires-Python: >=3.7,<4.0
Classifier: Programming Language :: Python :: 3
Classifier: Programming Language :: Python :: 3.10
Classifier: Programming Language :: Python :: 3.7
Classifier: Programming Language :: Python :: 3.8
Classifier: Programming Language :: Python :: 3.9
Requires-Dist: poetry (>=1.2.0b1,<2.0.0)
